palanteer/__init__.py
palanteer/__main__.py
palanteer/_cextension.cp313-win_amd64.pyd
palanteer-0.8.0.dist-info/licenses/LICENSE
palanteer-0.8.0.dist-info/METADATA
palanteer-0.8.0.dist-info/WHEEL
palanteer-0.8.0.dist-info/top_level.txt
palanteer-0.8.0.dist-info/RECORD
